payrix/__init__.py
payrix/api_helper.py
payrix/configuration.py
payrix/payrix_client.py
payrix/controllers/__init__.py
payrix/controllers/accounts_controller.py
payrix/controllers/accounts_verifications_controller.py
payrix/controllers/adjustments_controller.py
payrix/controllers/aggregation_result_groups_controller.py
payrix/controllers/aggregation_results_controller.py
payrix/controllers/aggregations_controller.py
payrix/controllers/alert_actions_controller.py
payrix/controllers/alert_triggers_controller.py
payrix/controllers/alerts_controller.py
payrix/controllers/api_keys_controller.py
payrix/controllers/apple_domains_controller.py
payrix/controllers/apple_domains_mass_enablement_controller.py
payrix/controllers/assessments_controller.py
payrix/controllers/authentication_tokens_controller.py
payrix/controllers/base_controller.py
payrix/controllers/batches_settlements_controller.py
payrix/controllers/billing_controller.py
payrix/controllers/billing_events_controller.py
payrix/controllers/billing_modifiers_controller.py
payrix/controllers/bins_controller.py
payrix/controllers/change_requests_controller.py
payrix/controllers/chargeback_documents_controller.py
payrix/controllers/chargeback_message_results_controller.py
payrix/controllers/chargeback_messages_controller.py
payrix/controllers/chargeback_statuses_controller.py
payrix/controllers/chargebacks_controller.py
payrix/controllers/confirmation_codes_controller.py
payrix/controllers/contacts_controller.py
payrix/controllers/credentials_controller.py
payrix/controllers/customers_controller.py
payrix/controllers/decision_actions_controller.py
payrix/controllers/decision_rules_controller.py
payrix/controllers/decisions_controller.py
payrix/controllers/disbursement_entries_controller.py
payrix/controllers/disbursement_reference_controller.py
payrix/controllers/disbursement_results_controller.py
payrix/controllers/disbursements_controller.py
payrix/controllers/divisions_controller.py
payrix_api_sdk-1.0.0.dist-info/licenses/LICENSE
payrix_api_sdk-1.0.0.dist-info/METADATA
payrix_api_sdk-1.0.0.dist-info/WHEEL
payrix_api_sdk-1.0.0.dist-info/top_level.txt
payrix_api_sdk-1.0.0.dist-info/RECORD
