Metadata-Version: 2.4
Name: payrix-api-sdk
Version: 1.0.0
Summary: SDKs for Payrix API
Author-email: Muhammad Rafay <muhammad.rafay@apimatic.io>
Project-URL: Documentation, https://docs.worldpay.com/apis/payrix
Requires-Python: >=3.7
License-File: LICENSE
Requires-Dist: apimatic-core>=0.2.23,~=0.2.0
Requires-Dist: apimatic-core-interfaces>=0.1.8,~=0.1.0
Requires-Dist: apimatic-requests-client-adapter>=0.1.9,~=0.1.0
Provides-Extra: testutils
Requires-Dist: pytest>=7.2.2; extra == "testutils"
Dynamic: license-file
